wtf_backhoe/__init__.py
wtf_backhoe-0.0.0.dist-info/LICENSE
wtf_backhoe-0.0.0.dist-info/METADATA
wtf_backhoe-0.0.0.dist-info/WHEEL
wtf_backhoe-0.0.0.dist-info/top_level.txt
wtf_backhoe-0.0.0.dist-info/RECORD
